{
  "__type__": "cc.TextAsset",
  "_name": "SCORING_SYSTEM_ANALYSIS",
  "_objFlags": 0,
  "__editorExtras__": {},
  "_native": "",
  "text": "# Scoring System Analysis & Balance\n\n## 📊 Game Mechanics Analysis\n\n### Positive Actions (Score Gain)\n\n| Action | Frequency | Difficulty | Base Score | Reasoning |\n|--------|-----------|------------|------------|-----------|\n| **Survival Time** | Continuous | Easy | **1 point/sec** | Passive reward for staying alive |\n| **Running** | Continuous | Easy | **2 points/sec** | Encourages movement |\n| **Wall Running** | Situational | Medium | **5 points/sec** | Requires skill + stamina management |\n| **Vaulting** | Per action | Medium | **10 points** | Requires timing + positioning |\n| **Jumping** | Per action | Easy | **3 points** | Basic parkour move |\n| **Dashing** | Per action | Medium | **8 points** | Requires stamina + cooldown management |\n| **Sliding** | Per action | Medium | **7 points** | Requires timing + momentum |\n| **Flag Collection Lv1** | Rare | Easy | **50 points** | Closest flags |\n| **Flag Collection Lv2** | Rare | Medium | **100 points** | Medium distance |\n| **Flag Collection Lv3** | Rare | Medium-Hard | **200 points** | Far distance |\n| **Flag Collection Lv4** | Very Rare | Hard | **350 points** | Very far distance |\n| **Flag Collection Lv5** | Very Rare | Very Hard | **500 points** | Farthest + legendary |\n| **Combo Multiplier** | Continuous | Hard | **x1.5 - x3.0** | Chaining actions without damage |\n\n### Negative Actions (Score Loss)\n\n| Action | Frequency | Impact | Score Penalty | Reasoning |\n|--------|-----------|--------|---------------|-----------|\n| **Taking Damage** | Occasional | Medium | **-20 points** | Punishment for poor play |\n| **Hitting Obstacle** | Occasional | Medium | **-15 points** | Collision penalty |\n| **Hitting Missile** | Occasional | High | **-30 points** | Harder to avoid |\n| **Falling into Survival Zone** | Rare | High | **-50 points** | Major mistake |\n| **Idling (>3 sec)** | Rare | Low | **-5 points/sec** | Discourages camping |\n\n### Multipliers & Bonuses\n\n| Condition | Multiplier | Duration | Notes |\n|-----------|------------|----------|-------|\n| **Flag Buff Active** | x1.0 - x3.0 | 10-20s | Based on flag level |\n| **Combo Chain (3+ actions)** | x1.2 | Until damage | Encourages aggressive play |\n| **Combo Chain (5+ actions)** | x1.5 | Until damage | Rewards skilled play |\n| **Combo Chain (10+ actions)** | x2.0 | Until damage | Master level |\n| **Perfect Run (No damage)** | x1.5 | Entire run | Bonus at end |\n| **Speed Bonus (>80% max speed)** | x1.1 | While fast | Encourages momentum |\n\n## 🎯 Balanced Scoring Values\n\n### Base Points Per Action\n\n```typescript\nexport enum ScoreValues {\n    // Continuous Actions (per second)\n    SURVIVAL = 1,\n    RUNNING = 2,\n    WALL_RUNNING = 5,\n    \n    // Single Actions\n    JUMP = 3,\n    SLIDE = 7,\n    DASH = 8,\n    VAULT = 10,\n    \n    // Flag Collection\n    FLAG_LEVEL_1 = 50,\n    FLAG_LEVEL_2 = 100,\n    FLAG_LEVEL_3 = 200,\n    FLAG_LEVEL_4 = 350,\n    FLAG_LEVEL_5 = 500,\n    \n    // Penalties\n    DAMAGE_TAKEN = -20,\n    OBSTACLE_HIT = -15,\n    MISSILE_HIT = -30,\n    SURVIVAL_ZONE_HIT = -50,\n    IDLE_PENALTY = -5,  // per second after 3 seconds\n}\n```\n\n## 📈 Score Progression Example\n\n**30-second run scenario:**\n\n```\nTime: 0-10s (Learning phase)\n- Survival: 10 points (10s × 1)\n- Running: 20 points (10s × 2)\n- 2 Jumps: 6 points (2 × 3)\n- 1 Vault: 10 points\n- Hit obstacle: -15 points\nSubtotal: 31 points\n\nTime: 10-20s (Getting better)\n- Survival: 10 points\n- Running: 16 points (8s × 2)\n- Wall Running: 10 points (2s × 5)\n- 1 Dash: 8 points\n- 1 Slide: 7 points\n- Combo x1.2: +6 points\nSubtotal: 57 points\n\nTime: 20-30s (Mastery + Flag)\n- Survival: 10 points\n- Running: 20 points (10s × 2)\n- Flag Lv3 collected: 200 points\n- Flag buff x2.0: +40 points (20s of actions)\n- Combo x1.5: +30 points\nSubtotal: 300 points\n\nTotal: 388 points in 30 seconds\n```\n\n## ⚖️ Balance Considerations\n\n### Why These Values?\n\n**1. Survival (1 pt/s)**\n- Base reward ensures everyone gets points\n- 60 points per minute is minimal but fair\n- Encourages staying alive\n\n**2. Running (2 pt/s)**\n- Double survival rate\n- Encourages movement over camping\n- 120 points per minute if constantly running\n\n**3. Wall Running (5 pt/s)**\n- 2.5x running rate\n- Requires skill + stamina management\n- High risk (can fall) = high reward\n\n**4. Parkour Moves (3-10 pts)**\n- Jump (3): Most common, lowest reward\n- Slide (7): Requires timing\n- Dash (8): Limited by cooldown + stamina\n- Vault (10): Requires obstacle + positioning\n\n**5. Flags (50-500 pts)**\n- Level 1 (50): Easy to reach, small bonus\n- Level 5 (500): Very far, huge reward\n- Risk/reward scales with distance\n- Rare spawns justify high values\n\n**6. Penalties (-15 to -50)**\n- Damage (-20): Moderate punishment\n- Obstacle (-15): Slightly less than damage\n- Missile (-30): Harder to avoid\n- Survival Zone (-50): Major mistake\n- Balanced to hurt but not devastate\n\n**7. Multipliers (x1.1 - x3.0)**\n- Flag buffs (x1.0-x3.0): Temporary power\n- Combo chains (x1.2-x2.0): Skill-based\n- Speed bonus (x1.1): Encourages momentum\n- Perfect run (x1.5): End-game bonus\n\n## 🎮 Gameplay Impact\n\n### Early Game (0-30s)\n- Focus: Learning mechanics\n- Expected Score: 50-150 points\n- Main Sources: Survival + basic parkour\n\n### Mid Game (30s-2min)\n- Focus: Chaining actions\n- Expected Score: 300-800 points\n- Main Sources: Combos + wall running\n\n### Late Game (2min+)\n- Focus: Flag hunting + combos\n- Expected Score: 1000+ points\n- Main Sources: Flags + multipliers\n\n### Skill Levels\n\n**Beginner (First try):**\n- 200-400 points in 1 minute\n- Mostly survival + running\n- Few parkour moves\n\n**Intermediate (Learning):**\n- 600-1000 points in 1 minute\n- Regular parkour moves\n- Some wall running\n- 1-2 flags collected\n\n**Advanced (Skilled):**\n- 1500-2500 points in 1 minute\n- Constant combos\n- Efficient wall running\n- 3-4 flags collected\n- Few mistakes\n\n**Master (Speedrunner):**\n- 3000+ points in 1 minute\n- Perfect combos\n- Flag buff stacking\n- No damage taken\n- Perfect run bonus\n\n## 🔄 Dynamic Difficulty Scaling\n\nAs game difficulty increases (Level 1-5):\n\n**Obstacles increase:**\n- More chances to lose points\n- But also more vaulting opportunities\n\n**Missiles increase:**\n- Higher penalty risk (-30)\n- But dodging gives combo points\n\n**Flags become more valuable:**\n- Higher level flags spawn\n- Greater risk = greater reward\n\n## 💡 Additional Mechanics\n\n### Combo System\n```\n3 actions without damage: x1.2\n5 actions without damage: x1.5\n10 actions without damage: x2.0\nDamage taken: Reset combo\n```\n\n### Speed Bonus\n```\nSpeed > 80% max speed: x1.1 multiplier\nEncourages maintaining momentum\n```\n\n### Perfect Run Bonus\n```\nComplete run without taking damage: x1.5 final score\nDisplayed at end screen\n```\n\n### Idle Penalty\n```\nNo movement for 3+ seconds: -5 points/second\nPrevents camping/AFK\n```\n\n## 📊 Score Display\n\n**During Gameplay:**\n- Current Score (top right)\n- Current Multiplier (below score)\n- Combo Counter (when active)\n- Score Popup (+X points) for actions\n\n**End Screen:**\n- Final Score\n- Breakdown by category\n- Highest Combo\n- Flags Collected\n- Perfect Run Bonus (if applicable)\n- Rank (D, C, B, A, S, SS)\n\n## 🏆 Ranking System\n\n| Rank | Score Range | Description |\n|------|-------------|-------------|\n| **D** | 0-500 | Beginner |\n| **C** | 501-1000 | Learning |\n| **B** | 1001-2000 | Competent |\n| **A** | 2001-3500 | Skilled |\n| **S** | 3501-5000 | Expert |\n| **SS** | 5001+ | Master |\n\n## 🎯 Summary\n\nThis scoring system:\n- ✅ Rewards skill and risk-taking\n- ✅ Punishes mistakes moderately\n- ✅ Encourages aggressive play\n- ✅ Scales with difficulty\n- ✅ Provides clear progression\n- ✅ Balances all mechanics\n- ✅ Creates replayability\n"
}